youtube_comment_downloader/__init__.py
youtube_comment_downloader/__main__.py
youtube_comment_downloader/downloader.py
youtube_comment_downloader-0.1.75.dist-info/LICENSE
youtube_comment_downloader-0.1.75.dist-info/METADATA
youtube_comment_downloader-0.1.75.dist-info/WHEEL
youtube_comment_downloader-0.1.75.dist-info/entry_points.txt
youtube_comment_downloader-0.1.75.dist-info/top_level.txt
youtube_comment_downloader-0.1.75.dist-info/RECORD
