Metadata-Version: 2.1
Name: youtube-comment-downloader
Version: 0.1.75
Summary: Simple script for downloading Youtube comments without using the Youtube API
Home-page: https://github.com/egbertbouman/youtube-comment-downloader
Author: Egbert Bouman
Author-email: ebouman@gmail.com
License: MIT
Classifier: License :: OSI Approved :: MIT License
Classifier: Environment :: Console
Classifier: Programming Language :: Python :: 2
Classifier: Programming Language :: Python :: 3
License-File: LICENSE
Requires-Dist: dateparser
Requires-Dist: requests
